main.py
meditationtimer-1.1.1.dist-info/METADATA
meditationtimer-1.1.1.dist-info/WHEEL
meditationtimer-1.1.1.dist-info/entry_points.txt
meditationtimer-1.1.1.dist-info/top_level.txt
meditationtimer-1.1.1.dist-info/RECORD
