Metadata-Version: 2.1
Name: meditationtimer
Version: 1.1.1
Summary: A small CLI meditation app for mindfullness sessions
Author-email: Folkert Jansen <fkjansen@protonmail.com>
Keywords: cli,meditation,click
Classifier: Programming Language :: Python :: 3
Classifier: Operating System :: OS Independent
Requires-Python: >=3.0
Requires-Dist: Click
